soundevent/__init__.py
soundevent/__version__.py
soundevent/constants.py
soundevent/operations.py
soundevent/py.typed
soundevent/types.py
soundevent/arrays/__init__.py
soundevent/arrays/attributes.py
soundevent/arrays/dimensions.py
soundevent/arrays/operations.py
soundevent/audio/__init__.py
soundevent/audio/attributes.py
soundevent/audio/files.py
soundevent/audio/io.py
soundevent/audio/media_info.py
soundevent/audio/operations.py
soundevent/audio/spectrograms.py
soundevent/data/__init__.py
soundevent/data/annotation_projects.py
soundevent/data/annotation_sets.py
soundevent/data/annotation_tasks.py
soundevent/data/clip_annotations.py
soundevent/data/clip_evaluations.py
soundevent/data/clip_predictions.py
soundevent/data/clips.py
soundevent/data/compat.py
soundevent/data/conftest.py
soundevent/data/datasets.py
soundevent/data/evaluation_sets.py
soundevent/data/evaluations.py
soundevent/data/features.py
soundevent/data/geometries.py
soundevent/data/matches.py
soundevent/data/model_runs.py
soundevent/data/notes.py
soundevent/data/predicted_tags.py
soundevent/data/prediction_sets.py
soundevent/data/recording_sets.py
soundevent/data/recordings.py
soundevent/data/sequence_annotations.py
soundevent/data/sequence_predictions.py
soundevent/data/sequences.py
soundevent/data/sound_event_annotations.py
soundevent/data/sound_event_predictions.py
soundevent/data/sound_events.py
soundevent/data/tags.py
soundevent/data/terms.py
soundevent/data/users.py
soundevent/data/uuids.py
soundevent/evaluation/__init__.py
soundevent/evaluation/affinity.py
soundevent/evaluation/encoding.py
soundevent/evaluation/match.py
soundevent/evaluation/metrics.py
soundevent/evaluation/tasks/__init__.py
soundevent/evaluation/tasks/clip_classification.py
soundevent/evaluation/tasks/clip_multilabel_classification.py
soundevent/evaluation/tasks/common.py
soundevent/evaluation/tasks/sound_event_classification.py
soundevent/evaluation/tasks/sound_event_detection.py
soundevent/geometry/__init__.py
soundevent-2.10.0.dist-info/METADATA
soundevent-2.10.0.dist-info/WHEEL
soundevent-2.10.0.dist-info/licenses/LICENSE
soundevent-2.10.0.dist-info/RECORD
