Metadata-Version: 2.4
Name: soundevent
Version: 2.10.0
Summary: soundevent is an open-source Python package for the computational biocoustic community, providing standardized tools for sound event analysis and data management.
Author-email: Santiago Martinez <santiago.balvanera.20@ucl.ac.uk>
License: MIT
License-File: LICENSE
Requires-Python: >=3.10
Requires-Dist: email-validator>=2.0
Requires-Dist: pydantic>=2.0
Provides-Extra: all
Requires-Dist: crowsetta>=5.0; extra == 'all'
Requires-Dist: cython>=0.29.36; extra == 'all'
Requires-Dist: matplotlib>=3.7.3; extra == 'all'
Requires-Dist: rasterio>=1.3.10; extra == 'all'
Requires-Dist: scikit-learn>=1.3.2; extra == 'all'
Requires-Dist: scipy>=1.6.1; extra == 'all'
Requires-Dist: shapely>=2.0.6; extra == 'all'
Requires-Dist: soundfile>=0.12.1; extra == 'all'
Requires-Dist: xarray>=0.20.2; extra == 'all'
Requires-Dist: xarray>=2023.1.0; extra == 'all'
Provides-Extra: audio
Requires-Dist: cython>=0.29.36; extra == 'audio'
Requires-Dist: scipy>=1.6.1; extra == 'audio'
Requires-Dist: soundfile>=0.12.1; extra == 'audio'
Requires-Dist: xarray>=0.20.2; extra == 'audio'
Provides-Extra: crowsetta
Requires-Dist: crowsetta>=5.0; extra == 'crowsetta'
Provides-Extra: evaluation
Requires-Dist: scikit-learn>=1.3.2; extra == 'evaluation'
Provides-Extra: geometry
Requires-Dist: rasterio>=1.3.10; extra == 'geometry'
Requires-Dist: shapely>=2.0.6; extra == 'geometry'
Requires-Dist: xarray>=2023.1.0; extra == 'geometry'
Provides-Extra: plot
Requires-Dist: matplotlib>=3.7.3; extra == 'plot'
